audius/__init__.py
audius/client.py
audius/client_factory.py
audius/config.py
audius/const.py
audius/exceptions.py
audius/playlists.py
audius/py.typed
audius/sdk.py
audius/session.py
audius/tips.py
audius/tracks.py
audius/types.py
audius/users.py
audius/version.py
audius/cli/__init__.py
audius/cli/config.py
audius/cli/playlists.py
audius/cli/tips.py
audius/cli/tracks.py
audius/cli/users.py
audius/cli/utils.py
audius/player/__init__.py
audius/player/af.py
audius/player/base.py
audius/player/vlc.py
audius_py-0.1.6.dist-info/LICENSE
audius_py-0.1.6.dist-info/METADATA
audius_py-0.1.6.dist-info/WHEEL
audius_py-0.1.6.dist-info/entry_points.txt
audius_py-0.1.6.dist-info/top_level.txt
audius_py-0.1.6.dist-info/RECORD
