Metadata-Version: 2.1
Name: audius-py
Version: 0.1.6
Summary: Interact with the Audius platform in Python and the terminal
Home-page: https://github.com/unparalleled-js/audius-py
Author: Juliya Smith <juliya@juliyasmith.com>
Author-email: juliya@juliyasmith.com
License: Apache-2.0
Keywords: audius
Classifier: Development Status :: 5 - Production/Stable
Classifier: Intended Audience :: Developers
Classifier: License :: OSI Approved :: MIT License
Classifier: Natural Language :: English
Classifier: Operating System :: MacOS
Classifier: Operating System :: POSIX
Classifier: Programming Language :: Python :: 3
Classifier: Programming Language :: Python :: 3.9
Classifier: Programming Language :: Python :: 3.10
Classifier: Programming Language :: Python :: 3.11
Classifier: Programming Language :: Python :: 3.12
Classifier: Programming Language :: Python :: 3.13
Requires-Python: >=3.9,<4
License-File: LICENSE
Requires-Dist: requests<3,>=2.32.3
Requires-Dist: cyclopts<4,>=3.4.1
Requires-Dist: tqdm<5,>=4.67.1
Requires-Dist: afplay-py<0.3,>=0.2.0
Provides-Extra: dev
Requires-Dist: pytest>=7.0; extra == "dev"
Requires-Dist: pytest-mock; extra == "dev"
Requires-Dist: black>=24.10.0; extra == "dev"
Requires-Dist: mypy<2,>=1.14.1; extra == "dev"
Requires-Dist: types-requests; extra == "dev"
Requires-Dist: types-setuptools; extra == "dev"
Requires-Dist: flake8>=7.1.1; extra == "dev"
Requires-Dist: flake8-type-checking; extra == "dev"
Requires-Dist: isort>=5.13.2; extra == "dev"
Requires-Dist: mdformat>=0.7.21; extra == "dev"
Requires-Dist: mdformat-gfm>=0.3.5; extra == "dev"
Requires-Dist: mdformat-frontmatter>=0.4.1; extra == "dev"
Requires-Dist: Sphinx<8,>=7.473; extra == "dev"
Requires-Dist: sphinx-rtd-theme<3,>=2.0.0; extra == "dev"
Requires-Dist: setuptools; extra == "dev"
Requires-Dist: setuptools-scm; extra == "dev"
Requires-Dist: wheel; extra == "dev"
Requires-Dist: twine==3.8; extra == "dev"
Requires-Dist: python-vlc<4,>=3.0.18121; extra == "dev"
Provides-Extra: doc
Requires-Dist: Sphinx<8,>=7.473; extra == "doc"
Requires-Dist: sphinx-rtd-theme<3,>=2.0.0; extra == "doc"
Provides-Extra: lint
Requires-Dist: black>=24.10.0; extra == "lint"
Requires-Dist: mypy<2,>=1.14.1; extra == "lint"
Requires-Dist: types-requests; extra == "lint"
Requires-Dist: types-setuptools; extra == "lint"
Requires-Dist: flake8>=7.1.1; extra == "lint"
Requires-Dist: flake8-type-checking; extra == "lint"
Requires-Dist: isort>=5.13.2; extra == "lint"
Requires-Dist: mdformat>=0.7.21; extra == "lint"
Requires-Dist: mdformat-gfm>=0.3.5; extra == "lint"
Requires-Dist: mdformat-frontmatter>=0.4.1; extra == "lint"
Provides-Extra: release
Requires-Dist: setuptools; extra == "release"
Requires-Dist: setuptools-scm; extra == "release"
Requires-Dist: wheel; extra == "release"
Requires-Dist: twine==3.8; extra == "release"
Provides-Extra: test
Requires-Dist: pytest>=7.0; extra == "test"
Requires-Dist: pytest-mock; extra == "test"
Provides-Extra: vlc
Requires-Dist: python-vlc<4,>=3.0.18121; extra == "vlc"
